{
  "category": "Tuck",
  "source_path": "dataset\\stitch code patterns\\Tuck\\002A_resized.png",
  "source_stem": "002A",
  "pairing_key": "2A",
  "simulation_path": "dataset\\simulation images\\Tuck\\002A.png",
  "source_size": [
    80,
    80
  ],
  "crop_box": [
    36,
    33,
    44,
    46
  ],
  "background_color": "#FF0000",
  "grid_rows": 13,
  "grid_columns": 8,
  "cell_width": 1,
  "cell_height": 1,
  "usable_size": [
    8,
    13
  ],
  "trimmed_width": 0,
  "trimmed_height": 0,
  "trimmed_pixel_count": 0,
  "warnings": [],
  "mean_quantization_distance": 31.442255,
  "max_quantization_distance": 46.281746,
  "average_cell_purity": 1.0,
  "ambiguous_cell_count": 0,
  "ambiguous_cells": [],
  "exact_pixel_match_ratio": 1.0
}